servitin/__init__.py
servitin/apps.py
servitin/base.py
servitin/log.py
servitin/settings.py
servitin/utils.py
servitin/lib/__init__.py
servitin/lib/postgres.py
servitin/lib/websocket_client.py
servitin/lib/zmq/__init__.py
servitin/lib/zmq/client.py
servitin/lib/zmq/server.py
servitin/management/__init__.py
servitin/management/commands/__init__.py
servitin/management/commands/run_servitin.py
servitin-1.0.4.dist-info/LICENSE
servitin-1.0.4.dist-info/METADATA
servitin-1.0.4.dist-info/WHEEL
servitin-1.0.4.dist-info/top_level.txt
servitin-1.0.4.dist-info/RECORD
