Metadata-Version: 2.1
Name: servitin
Version: 1.0.4
Summary: Django services app
Home-page: https://github.com/avigmati/servitin
Author: Dmitry Novikov
Author-email: avigmati@gmail.com
License: UNKNOWN
Project-URL: Bug Tracker, https://github.com/avigmati/servitin/issues
Platform: UNKNOWN
Classifier: Programming Language :: Python :: 3
Classifier: License :: OSI Approved :: MIT License
Classifier: Operating System :: OS Independent
Requires-Python: >=3.9
License-File: LICENSE
Requires-Dist: aiozmq (>=0.9.0)
Requires-Dist: async-timeout (>=3.0.1)
Requires-Dist: msgpack (>=1.0.2)
Requires-Dist: pydantic (>=1.8.2)
Requires-Dist: python-jose (>=3.3.0)
